acore_soap_agent/__init__.py
acore_soap_agent/_version.py
acore_soap_agent/api.py
acore_soap_agent/paths.py
acore_soap_agent/request.py
acore_soap_agent/utils.py
acore_soap_agent/cli/__init__.py
acore_soap_agent/cli/impl.py
acore_soap_agent/cli/main.py
acore_soap_agent/docs/__init__.py
acore_soap_agent/tests/__init__.py
acore_soap_agent/tests/helper.py
acore_soap_agent/vendor/__init__.py
acore_soap_agent/vendor/pytest_cov_helper.py
acore_soap_agent-0.2.1.dist-info/AUTHORS.rst
acore_soap_agent-0.2.1.dist-info/LICENSE.txt
acore_soap_agent-0.2.1.dist-info/METADATA
acore_soap_agent-0.2.1.dist-info/WHEEL
acore_soap_agent-0.2.1.dist-info/entry_points.txt
acore_soap_agent-0.2.1.dist-info/top_level.txt
acore_soap_agent-0.2.1.dist-info/RECORD
